seakybox/__init__.py
seakybox/data/__init__.py
seakybox/data/mongo_func.py
seakybox/data/mysql.py
seakybox/data/mysql_pd.py
seakybox/data/pd.py
seakybox/data/redis_func.py
seakybox/func/__init__.py
seakybox/func/base.py
seakybox/func/ctf.py
seakybox/func/interactive.py
seakybox/func/log.py
seakybox/func/misc.py
seakybox/func/mrun.py
seakybox/func/number.py
seakybox/func/parser.py
seakybox/func/string.py
seakybox/func/time.py
seakybox/misc/__init__.py
seakybox/misc/ctf.py
seakybox/misc/token.py
seakybox/net/__init__.py
seakybox/net/connectivity.py
seakybox/net/http.py
seakybox/net/ip.py
seakybox/net/proxy.py
seakybox/net/sserver.py
seakybox/notify/__init__.py
seakybox/notify/dingding.py
seakybox/notify/ftqq.py
seakybox/notify/im.py
seakybox/notify/sendmail.py
seakybox/os/__init__.py
seakybox/os/cmd.py
seakybox/os/compress.py
seakybox/os/info.py
seakybox/os/oper.py
seakybox-0.2.dist-info/LICENSE
seakybox-0.2.dist-info/METADATA
seakybox-0.2.dist-info/WHEEL
seakybox-0.2.dist-info/top_level.txt
seakybox-0.2.dist-info/RECORD
